satori_ci-1.79.0.dist-info/METADATA
satori_ci-1.79.0.dist-info/WHEEL
satori_ci-1.79.0.dist-info/entry_points.txt
satori_ci-1.79.0.dist-info/licenses/LICENSE
satoricli/__init__.py
satoricli/__main__.py
satoricli/api.py
satoricli/bundler.py
satoricli/cli/__init__.py
satoricli/cli/arguments.py
satoricli/cli/commands/base.py
satoricli/cli/commands/config.py
satoricli/cli/commands/dashboard.py
satoricli/cli/commands/help.py
satoricli/cli/commands/install.py
satoricli/cli/commands/local.py
satoricli/cli/commands/monitor.py
satoricli/cli/commands/monitors.py
satoricli/cli/commands/playbook.py
satoricli/cli/commands/playbooks.py
satoricli/cli/commands/repo.py
satoricli/cli/commands/report.py
satoricli/cli/commands/reports.py
satoricli/cli/commands/repos.py
satoricli/cli/commands/root.py
satoricli/cli/commands/run.py
satoricli/cli/commands/scan.py
satoricli/cli/commands/scans.py
satoricli/cli/commands/settings.py
satoricli/cli/commands/shards.py
satoricli/cli/commands/team.py
satoricli/cli/commands/teams.py
satoricli/cli/commands/template.py
satoricli/cli/commands/templates.py
satoricli/cli/commands/update.py
satoricli/cli/commands/whoami.py
satoricli/cli/commands/width.py
satoricli/cli/utils.py
satoricli/exceptions.py
satoricli/playbooks.py
satoricli/utils.py
satoricli/validations.py
satori_ci-1.79.0.dist-info/RECORD
