Metadata-Version: 2.1
Name: satori-ci
Version: 1.79.0
Summary: Satori CI - Automated Testing
Author-Email: Satori CI CLI <info@satori.ci>
License:                     GNU GENERAL PUBLIC LICENSE
Project-URL: Homepage, https://satori.ci
Requires-Python: >=3.10
Requires-Dist: satori-playbook-validator>=3.7.20
Requires-Dist: satori-docs==1.3.5
Requires-Dist: pyyaml>=6.0
Requires-Dist: flatdict>=4.0.1
Requires-Dist: rich>=13.0
Requires-Dist: gitpython>=3.1.31
Requires-Dist: packaging>=23.1
Requires-Dist: websocket-client>=1.6.1
Requires-Dist: httpx>=0.24.1
Requires-Dist: satori-runner==0.1.2
Requires-Dist: numpy>=2.2.6
Requires-Dist: netaddr>=1.3.0
Requires-Dist: httpx-retries>=0.4.5
